pyLife360/__init__.py
pyLife360/life360.py
pyLife360-1.0.3.dist-info/LICENSE
pyLife360-1.0.3.dist-info/METADATA
pyLife360-1.0.3.dist-info/WHEEL
pyLife360-1.0.3.dist-info/top_level.txt
pyLife360-1.0.3.dist-info/RECORD
