Metadata-Version: 2.1
Name: pyLife360
Version: 1.0.3
Summary: pyLife360 is a simple library to rip data from Life360's unoffical API.
Home-page: https://github.com/Xisurthros/pyLife360
Author: Jacob Hobbs
Author-email: jacobcoburnhobbs@gmail.com
Project-URL: Bug Tracker, https://github.com/Xisurthros/pyLife360/issues
Classifier: Programming Language :: Python :: 3
Classifier: License :: OSI Approved :: MIT License
Classifier: Operating System :: OS Independent
Requires-Python: >=3.7
License-File: LICENSE
